fairdetect/__init__.py
fairdetect-0.5.dist-info/METADATA
fairdetect-0.5.dist-info/WHEEL
fairdetect-0.5.dist-info/fairdetect_package - Acceso directo.lnk
fairdetect-0.5.dist-info/top_level.txt
fairdetect-0.5.dist-info/RECORD
